shtst.py
shtst-0.1.1.dist-info/LICENSE.GPLv3
shtst-0.1.1.dist-info/METADATA
shtst-0.1.1.dist-info/WHEEL
shtst-0.1.1.dist-info/entry_points.txt
shtst-0.1.1.dist-info/top_level.txt
shtst-0.1.1.dist-info/RECORD
