Metadata-Version: 2.1
Name: shtst
Version: 0.1.1
Summary: simple cli testing
Home-page: https://github.com/obfusk/shtst
Author: Felix C. Stegerman
Author-email: flx@obfusk.net
License: GPLv3+
Keywords: shell sh bash test cli
Platform: UNKNOWN
Classifier: Development Status :: 4 - Beta
Classifier: Environment :: Console
Classifier: Intended Audience :: Developers
Classifier: License :: OSI Approved :: GNU General Public License v3 or later (GPLv3+)
Classifier: Operating System :: POSIX :: Linux
Classifier: Programming Language :: Python :: 3
Classifier: Programming Language :: Python :: 3.7
Classifier: Programming Language :: Python :: 3.8
Classifier: Programming Language :: Python :: 3.9
Classifier: Programming Language :: Python :: Implementation :: CPython
Classifier: Topic :: Software Development
Classifier: Topic :: Utilities
Requires-Python: >=3.7
Requires-Dist: click (>=6.0)
